android_sdk_supporter/__init__.py
android_sdk_supporter/build_tools.py
android_sdk_supporter/cmdline_tools.py
android_sdk_supporter/platform_tools.py
android_sdk_supporter-0.0.6.dist-info/METADATA
android_sdk_supporter-0.0.6.dist-info/WHEEL
android_sdk_supporter-0.0.6.dist-info/top_level.txt
android_sdk_supporter-0.0.6.dist-info/RECORD
