Metadata-Version: 2.1
Name: android-sdk-supporter
Version: 0.0.6
Summary: Android sdk supporter
Home-page: https://github.com/automatethem/android-sdk-supporter
Author: Sang Ki Kwon
Author-email: automatethem@gmail.com
License: MIT
